{
  "session_id": "20250813_174532",
  "timestamp": "2025-08-13T17:45:32.590436",
  "original_text": "민주님 어서 오세요. 일주일 동안 어떻게 지내셨어요? 표정이 지난번보다 더 어두워 보이세요. 안녕하세요, 선생님. 뇌, 솔직히 말씀드리면 지난주보다 더 나빠졌으면 나빠졌지, 좋아진 건 하나도 없는 것 같아요. 매일매일이 낭떠러지 끝에 서 있는 기분입니다. 낭떠러지 끝에 서 있는 기분이라고 하셨어요. 어떤 점이 민주님을 그렇게 느끼게 만들었을까요? 지난번에 이야기 나눴던 프로젝트와 관련된 일인가요? 매일 맞아요, 그놈의 프로젝트가 뭔지. 지난주에 말씀드렸던 박서준 팀장과의 일이 있고 나서 상황이 더 안 좋아졌어요. 8월 6일 수요일에 있었던 일 말씀이시죠? 팀원들 앞에서 기획안에 대해 면박을 주셨다는 그 이후에 어떤 일이 더 있었나요? 그날 이후로 팀장님은 저를 거의 투명인간 취급하고 있어요. 업무 보고를 하러 가도 쳐다보지도 않고 메신저로만 지시하고요. 같은 팀 이지은 대리는 제 눈치를 보고, 몇몇 동료들은 아예 저를 피하는 게 느껴져요. 제가 무슨 전염병 환자가 된 것 같아요. 팀 안에서 고립감을 느끼고 계시는군요. 그런 상황에서 민주님 편이 되어준 사람은 아무도 없었나요? 다행히 입사 동기인 최유리 사원이 점심시간에 따로 불러내서 위로해주긴 했어요. 팀장님 원래 저러시는 거 알잖아요. 너무 마음에 담아두지 마세요 하고요. 유리 씨 연락처가 010-5554-444인데 고맙다고 커피 쿠폰이라도 보내줘야겠어요. 하지만 그런 위로도 잠시뿐, 제 마음은 조금도 나아지지가 않네요. 잠시나마 위로가 되는 순간도 있었지만 근본적인 괴로움은 해소되지 않으셨군요. 매 스트레스가 극에 달하니까 몸이 먼저 신호를 보내더라고요. 지난 월요일 새벽, 갑자기 위가 너무 아파서 잠에서 깼어요. 위경련인 것 같았는데 정말 데굴데굴 구를 정도로 아팠습니다. 결국 아침에 연차를 내고 집 근처 병원에 다녀왔어요. 저런 몸까지 아프셨다니 정말 힘드셨겠어요. 어느 병원에 다녀오셨어요? 저희 집이 서울시 마포구 합정동 123에 45, 메세나폴리스 아파트 101동 152호잖아요. 바로 앞에 있는 연세마음 클리닉에 갔어요. 거기 이선영 원장님이 보시더니 스트레스성 위염이랑 역류성 식도염이 심하다고 약 먹으면서 무조건 쉬어야 한다고 하시더라고요. 근데 쉴 수 있는 상황이 아니잖아요. 제가 의사는 휴식을 권했지만 현실적으로 쉴 수 없는 상황 때문에 더 답답하고 무력감을 느끼셨겠어요.",
  "masked_text": "[개인정보]님 어서 오세요. 일주일 동안 어떻게 지내셨어요? 표정이 지난번보다 더 어두워 보이세요. 안녕하세요, [개인정보]님. 뇌, 솔직히 말씀드리면 지난주보다 더 나빠졌으면 나빠졌지, 좋아진 건 하나도 없는 것 같아요. 매일매일이 낭떠러지 끝에 서 있는 기분입니다. 낭떠러지 끝에 서 있는 기분이라고 하셨어요. 어떤 점이 [개인정보]님을 그렇게 느끼게 만들었을까요? 지난번에 이야기 나눴던 프로젝트와 관련된 일인가요? 매일 맞아요, 그놈의 프로젝트가 뭔지. 지난주에 말씀드렸던 [개인정보] [개인정보]과의 일이 있고 나서 상황이 더 안 좋아졌어요. 8월 6일 수요일에 있었던 일 말씀이시죠? [개인정보]들 앞에서 기획안에 대해 면박을 주셨다는 그 이후에 어떤 일이 더 있었나요? 그날 이후로 [개인정보]님은 저를 거의 투명인간 취급하고 있어요. 업무 보고를 하러 가도 쳐다보지도 않고 메신저로만 지시하고요. 같은 팀 [개인정보] [개인정보]는 제 눈치를 보고, 몇몇 동료들은 아예 저를 피하는 게 느껴져요. 제가 무슨 전염병 [개인정보]가 된 것 같아요. 팀 안에서 고립감을 느끼고 계시는군요. 그런 상황에서 민주님 편이 되어준 사람은 아무도 없었나요? 다행히 입사 동기인 [개인정보] [개인정보]이 점심시간에 따로 불러내서 위로해주긴 했어요. [개인정보]님 원래 저러시는 거 알잖아요. 너무 마음에 담아두지 마세요 하고요. [개인정보] 씨 연락처가 [개인정보]인데 고맙다고 커피 쿠폰이라도 보내줘야겠어요. 하지만 그런 위로도 잠시뿐, 제 마음은 조금도 나아지지가 않네요. 잠시나마 위로가 되는 순간도 있었지만 근본적인 괴로움은 해소되지 않으셨군요. 매 [개인정보]가 극에 달하니까 몸이 먼저 신호를 보내더라고요. 지난 월요일 새벽, 갑자기 위가 너무 아파서 잠에서 깼어요. [개인정보]인 것 같았는데 정말 데굴데굴 구를 정도로 아팠습니다. 결국 아침에 연차를 내고 집 근처 병원에 다녀왔어요. 저런 몸까지 아프셨다니 정말 힘드셨겠어요. 어느 병원에 다녀오셨어요? 저희 집이 서울시 [개인정보] [개인정보] 123에 45, [개인정보] 101동 152호잖아요. 바로 앞에 있는 연세마음 클리닉에 갔어요. 거기 [개인정보] [개인정보]님이 보시더니 [개인정보]성 [개인정보]이랑 [개인정보]이 심하다고 약 먹으면서 무조건 쉬어야 한다고 하시더라고요. 근데 쉴 수 있는 상황이 아니잖아요. 제가 [개인정보]는 휴식을 권했지만 현실적으로 쉴 수 없는 상황 때문에 더 답답하고 무력감을 느끼셨겠어요.",
  "masking_rules": {
    "mode": "simple",
    "simple_rule": "[개인정보]"
  },
  "records": [
    {
      "entity_id": "20250813_174532_0000",
      "original_text": "의사",
      "masked_text": "[개인정보]",
      "label": "신원",
      "subtype": "직업",
      "start": 1107,
      "end": 1109,
      "metadata": {
        "source": "etri",
        "confidence": 0.95
      }
    },
    {
      "entity_id": "20250813_174532_0001",
      "original_text": "역류성 식도염",
      "masked_text": "[개인정보]",
      "label": "신원",
      "subtype": "건강정보",
      "start": 1042,
      "end": 1049,
      "metadata": {
        "source": "etri",
        "confidence": 0.95
      }
    },
    {
      "entity_id": "20250813_174532_0002",
      "original_text": "위염",
      "masked_text": "[개인정보]",
      "label": "신원",
      "subtype": "건강정보",
      "start": 1037,
      "end": 1039,
      "metadata": {
        "source": "etri",
        "confidence": 0.95
      }
    },
    {
      "entity_id": "20250813_174532_0003",
      "original_text": "스트레스",
      "masked_text": "[개인정보]",
      "label": "신원",
      "subtype": "건강정보",
      "start": 1031,
      "end": 1035,
      "metadata": {
        "source": "etri",
        "confidence": 0.95
      }
    },
    {
      "entity_id": "20250813_174532_0004",
      "original_text": "원장",
      "masked_text": "[개인정보]",
      "label": "신원",
      "subtype": "직위",
      "start": 1021,
      "end": 1023,
      "metadata": {
        "source": "etri",
        "confidence": 0.95
      }
    },
    {
      "entity_id": "20250813_174532_0005",
      "original_text": "이선영",
      "masked_text": "[개인정보]",
      "label": "이름",
      "subtype": "인명",
      "start": 1017,
      "end": 1020,
      "metadata": {
        "source": "etri",
        "confidence": 0.95
      }
    },
    {
      "entity_id": "20250813_174532_0006",
      "original_text": "메세나폴리스 아파트",
      "masked_text": "[개인정보]",
      "label": "주소",
      "subtype": "건물명",
      "start": 965,
      "end": 975,
      "metadata": {
        "source": "etri",
        "confidence": 0.95
      }
    },
    {
      "entity_id": "20250813_174532_0007",
      "original_text": "합정동",
      "masked_text": "[개인정보]",
      "label": "주소",
      "subtype": "군/구/동",
      "start": 952,
      "end": 955,
      "metadata": {
        "source": "etri",
        "confidence": 0.95
      }
    },
    {
      "entity_id": "20250813_174532_0008",
      "original_text": "마포구",
      "masked_text": "[개인정보]",
      "label": "주소",
      "subtype": "군/구/동",
      "start": 948,
      "end": 951,
      "metadata": {
        "source": "etri",
        "confidence": 0.95
      }
    },
    {
      "entity_id": "20250813_174532_0009",
      "original_text": "위경련",
      "masked_text": "[개인정보]",
      "label": "신원",
      "subtype": "건강정보",
      "start": 835,
      "end": 838,
      "metadata": {
        "source": "etri",
        "confidence": 0.95
      }
    },
    {
      "entity_id": "20250813_174532_0010",
      "original_text": "스트레스",
      "masked_text": "[개인정보]",
      "label": "신원",
      "subtype": "건강정보",
      "start": 769,
      "end": 773,
      "metadata": {
        "source": "etri",
        "confidence": 0.95
      }
    },
    {
      "entity_id": "20250813_174532_0011",
      "original_text": "010-5554-444",
      "masked_text": "[개인정보]",
      "label": "번호",
      "subtype": "전화번호",
      "start": 649,
      "end": 661,
      "metadata": {
        "source": "etri",
        "confidence": 0.95
      }
    },
    {
      "entity_id": "20250813_174532_0012",
      "original_text": "유리",
      "masked_text": "[개인정보]",
      "label": "이름",
      "subtype": "인명",
      "start": 639,
      "end": 641,
      "metadata": {
        "source": "etri",
        "confidence": 0.95
      }
    },
    {
      "entity_id": "20250813_174532_0013",
      "original_text": "팀장",
      "masked_text": "[개인정보]",
      "label": "신원",
      "subtype": "직위",
      "start": 598,
      "end": 600,
      "metadata": {
        "source": "etri",
        "confidence": 0.95
      }
    },
    {
      "entity_id": "20250813_174532_0014",
      "original_text": "사원",
      "masked_text": "[개인정보]",
      "label": "신원",
      "subtype": "직위",
      "start": 569,
      "end": 571,
      "metadata": {
        "source": "etri",
        "confidence": 0.95
      }
    },
    {
      "entity_id": "20250813_174532_0015",
      "original_text": "최유리",
      "masked_text": "[개인정보]",
      "label": "이름",
      "subtype": "인명",
      "start": 565,
      "end": 568,
      "metadata": {
        "source": "etri",
        "confidence": 0.95
      }
    },
    {
      "entity_id": "20250813_174532_0016",
      "original_text": "환자",
      "masked_text": "[개인정보]",
      "label": "신원",
      "subtype": "직위",
      "start": 486,
      "end": 488,
      "metadata": {
        "source": "etri",
        "confidence": 0.95
      }
    },
    {
      "entity_id": "20250813_174532_0017",
      "original_text": "대리",
      "masked_text": "[개인정보]",
      "label": "신원",
      "subtype": "직위",
      "start": 436,
      "end": 438,
      "metadata": {
        "source": "etri",
        "confidence": 0.95
      }
    },
    {
      "entity_id": "20250813_174532_0018",
      "original_text": "이지은",
      "masked_text": "[개인정보]",
      "label": "이름",
      "subtype": "인명",
      "start": 432,
      "end": 435,
      "metadata": {
        "source": "etri",
        "confidence": 0.95
      }
    },
    {
      "entity_id": "20250813_174532_0019",
      "original_text": "팀장",
      "masked_text": "[개인정보]",
      "label": "신원",
      "subtype": "직위",
      "start": 366,
      "end": 368,
      "metadata": {
        "source": "etri",
        "confidence": 0.95
      }
    },
    {
      "entity_id": "20250813_174532_0020",
      "original_text": "팀원",
      "masked_text": "[개인정보]",
      "label": "신원",
      "subtype": "직위",
      "start": 314,
      "end": 316,
      "metadata": {
        "source": "etri",
        "confidence": 0.95
      }
    },
    {
      "entity_id": "20250813_174532_0021",
      "original_text": "팀장",
      "masked_text": "[개인정보]",
      "label": "신원",
      "subtype": "직위",
      "start": 261,
      "end": 263,
      "metadata": {
        "source": "etri",
        "confidence": 0.95
      }
    },
    {
      "entity_id": "20250813_174532_0022",
      "original_text": "박서준",
      "masked_text": "[개인정보]",
      "label": "이름",
      "subtype": "인명",
      "start": 257,
      "end": 260,
      "metadata": {
        "source": "etri",
        "confidence": 0.95
      }
    },
    {
      "entity_id": "20250813_174532_0023",
      "original_text": "민주",
      "masked_text": "[개인정보]",
      "label": "소속",
      "subtype": "정부기관",
      "start": 174,
      "end": 176,
      "metadata": {
        "source": "etri",
        "confidence": 0.95
      }
    },
    {
      "entity_id": "20250813_174532_0024",
      "original_text": "선생",
      "masked_text": "[개인정보]",
      "label": "신원",
      "subtype": "직위",
      "start": 59,
      "end": 61,
      "metadata": {
        "source": "etri",
        "confidence": 0.95
      }
    },
    {
      "entity_id": "20250813_174532_0025",
      "original_text": "민주",
      "masked_text": "[개인정보]",
      "label": "신원",
      "subtype": "직위",
      "start": 0,
      "end": 2,
      "metadata": {
        "source": "etri",
        "confidence": 0.95
      }
    }
  ],
  "stats": {
    "total_masked": 26,
    "text_length": 1159,
    "masked_length": 1229
  }
}